PEMFileGenerator/__init__.py
PEMFileGenerator/__version__.py
PEMFileGenerator/ssh_pem.py
PEMFileGenerator-0.0.3.dist-info/LICENSE
PEMFileGenerator-0.0.3.dist-info/METADATA
PEMFileGenerator-0.0.3.dist-info/WHEEL
PEMFileGenerator-0.0.3.dist-info/top_level.txt
PEMFileGenerator-0.0.3.dist-info/RECORD
