Metadata-Version: 2.1
Name: PEMFileGenerator
Version: 0.0.3
Summary: This package will help to generate SSH PEM File for access server
Home-page: https://github.com/vubon/PEMFileGenerator
Author: Vubon Roy
Author-email: vubon.roy@gmail.com
License: MIT
Project-URL: Documentation, https://github.com/vubon/PEMFileGenerator/blob/master/docs/GUIDE.md
Platform: Python
Classifier: License :: OSI Approved :: MIT License
Classifier: Environment :: Web Environment
Classifier: Intended Audience :: Developers
Classifier: Programming Language :: Python :: 3 :: Only
Classifier: Programming Language :: Python :: 3.6
Classifier: Programming Language :: Python :: 3.7
Classifier: Programming Language :: Python :: 3.8
Classifier: Programming Language :: Python :: 3.9
Classifier: Operating System :: OS Independent
Classifier: Natural Language :: English
Classifier: Topic :: Software Development :: Libraries :: Python Modules
License-File: LICENSE
Requires-Dist: fabric
